SacraMathEngine/Matrix.py
SacraMathEngine/MeshObject.py
SacraMathEngine/Triangle.py
SacraMathEngine/Vector.py
SacraMathEngine/__init__.py
SacraMathEngine-0.0.9.dist-info/LICENSE
SacraMathEngine-0.0.9.dist-info/METADATA
SacraMathEngine-0.0.9.dist-info/WHEEL
SacraMathEngine-0.0.9.dist-info/top_level.txt
SacraMathEngine-0.0.9.dist-info/RECORD
